{
  "rpc": "https://scrt.public-rpc.com",
  "rest": "https://lcd.mainnet.secretsaturn.net",
  "chainId": "secret-4",
  "chainName": "Secret Network",
  "chainSymbolImageUrl": "https://raw.githubusercontent.com/chainapsis/keplr-chain-registry/main/images/secret/chain.png",
  "stakeCurrency": {
    "coinDenom": "SCRT",
    "coinMinimalDenom": "uscrt",
    "coinDecimals": 6,
    "coinGeckoId": "secret",
    "coinImageUrl": "https://raw.githubusercontent.com/chainapsis/keplr-chain-registry/main/images/secret/uscrt.png"
  },
  "walletUrl": "https://wallet.keplr.app/chains/secret-network",
  "walletUrlForStaking": "https://wallet.keplr.app/chains/secret-network",
  "bip44": {
    "coinType": 529
  },
  "alternativeBIP44s": [
    {
      "coinType": 118
    }
  ],
  "bech32Config": {
    "bech32PrefixAccAddr": "secret",
    "bech32PrefixAccPub": "secretpub",
    "bech32PrefixValAddr": "secretvaloper",
    "bech32PrefixValPub": "secretvaloperpub",
    "bech32PrefixConsAddr": "secretvalcons",
    "bech32PrefixConsPub": "secretvalconspub"
  },
  "currencies": [
    {
      "coinDenom": "SCRT",
      "coinMinimalDenom": "uscrt",
      "coinDecimals": 6,
      "coinGeckoId": "secret",
      "coinImageUrl": "https://raw.githubusercontent.com/chainapsis/keplr-chain-registry/main/images/secret/uscrt.png",
      "cosmos": {
        "minimalDenom": "uscrt"
      },
      "polkadot": {},
      "ethereum": {
        "minimalDenom": "transfer/channel-2/transfer/channel-14/uscrt",
        "erc20Address": "0xF7F00d598b2a651404993E93Df7AE16C3C736F3C",
        "fromCosmosFee": 34,
        "minimumTransfer": 80
      },
      "solana": {
        "mintAddress": "6bQZs6ZSaRoaYPsfLibM9ZhZa4Haj4xF5uFJ33Kduc3V",
        "minimalDenom": "transfer/channel-1/transfer/channel-14/uscrt1",
        "minimumTransfer": 50,
        "fromCosmosFee": 0,
        "displayDecimals": 0
      }
    }
  ],
  "feeCurrencies": [
    {
      "coinDenom": "SCRT",
      "coinMinimalDenom": "uscrt",
      "coinDecimals": 6,
      "coinGeckoId": "secret",
      "coinImageUrl": "https://raw.githubusercontent.com/chainapsis/keplr-chain-registry/main/images/secret/uscrt.png",
      "gasPriceStep": {
        "low": 0.05,
        "average": 0.1,
        "high": 0.25
      }
    }
  ],
  "features": [
    "secretwasm",
    "authz-msg-revoke-fixed"
  ],
  "chainType": "cosmos",
  "channelMap": {
    "1": "centauri-1",
    "5": "----"
  },
  "cosmos": {
    "bip44": {
      "coinType": 529
    },
    "bech32Config": {
      "bech32PrefixAccAddr": "secret",
      "bech32PrefixAccPub": "secretpub",
      "bech32PrefixValAddr": "secretvaloper",
      "bech32PrefixValPub": "secretvaloperpub",
      "bech32PrefixConsAddr": "secretvalcons",
      "bech32PrefixConsPub": "secretvalconspub"
    }
  }
}